dbt_autofix-0.18.7.dist-info/METADATA
dbt_autofix-0.18.7.dist-info/WHEEL
dbt_autofix-0.18.7.dist-info/entry_points.txt
dbt_autofix-0.18.7.dist-info/licenses/LICENSE
dbt_autofix/__init__.py
dbt_autofix/dbt_api.py
dbt_autofix/deprecations.py
dbt_autofix/duplicate_keys.py
dbt_autofix/fields_properties_configs.py
dbt_autofix/hub_packages.py
dbt_autofix/jinja.py
dbt_autofix/main.py
dbt_autofix/package_upgrade.py
dbt_autofix/packages/__init__.py
dbt_autofix/packages/dbt_package_file.py
dbt_autofix/packages/dbt_package_text_file.py
dbt_autofix/packages/installed_packages.py
dbt_autofix/packages/package_hub_client.py
dbt_autofix/refactor.py
dbt_autofix/refactors/__init__.py
dbt_autofix/refactors/changesets/__init__.py
dbt_autofix/refactors/changesets/dbt_project_yml.py
dbt_autofix/refactors/changesets/dbt_schema_yml.py
dbt_autofix/refactors/changesets/dbt_schema_yml_semantic_layer.py
dbt_autofix/refactors/changesets/dbt_sql.py
dbt_autofix/refactors/changesets/dbt_sql_improved.py
dbt_autofix/refactors/constants.py
dbt_autofix/refactors/fancy_quotes_utils.py
dbt_autofix/refactors/results.py
dbt_autofix/refactors/yml.py
dbt_autofix/retrieve_schemas.py
dbt_autofix/semantic_definitions.py
packages/dbt_fusion_package_tools/.gitignore
packages/dbt_fusion_package_tools/.pdm-build/.gitignore
packages/dbt_fusion_package_tools/.pdm-build/pyproject.toml
packages/dbt_fusion_package_tools/.python-version
packages/dbt_fusion_package_tools/README.md
packages/dbt_fusion_package_tools/pdm_build.py
packages/dbt_fusion_package_tools/pyproject.toml
packages/dbt_fusion_package_tools/src/dbt_fusion_package_tools/__init__.py
packages/dbt_fusion_package_tools/src/dbt_fusion_package_tools/check_parse_conformance.py
packages/dbt_fusion_package_tools/src/dbt_fusion_package_tools/compatibility.py
packages/dbt_fusion_package_tools/src/dbt_fusion_package_tools/dbt_package.py
packages/dbt_fusion_package_tools/src/dbt_fusion_package_tools/dbt_package_version.py
packages/dbt_fusion_package_tools/src/dbt_fusion_package_tools/exceptions.py
packages/dbt_fusion_package_tools/src/dbt_fusion_package_tools/fusion_version_compatibility_output.py
dbt_autofix-0.18.7.dist-info/RECORD
